pybasecurl/__init__.py
pybasecurl/cli.py
pybasecurl/curl.py
pybasecurl/storage.py
pybasecurl-0.0.3.dist-info/LICENSE
pybasecurl-0.0.3.dist-info/METADATA
pybasecurl-0.0.3.dist-info/WHEEL
pybasecurl-0.0.3.dist-info/entry_points.txt
pybasecurl-0.0.3.dist-info/top_level.txt
pybasecurl-0.0.3.dist-info/RECORD
