Metadata-Version: 2.1
Name: pybasecurl
Version: 0.0.3
Summary: A curl package for python
Author-email: Pybase <techlead@sonnm.com>
Project-URL: Homepage, https://github.com/pybase-net/pycurl
Project-URL: Bug Tracker, https://github.com/pybase-net/pycurl/issues
Classifier: Programming Language :: Python :: 3
Classifier: License :: OSI Approved :: MIT License
Classifier: Operating System :: OS Independent
Requires-Python: >=3.9
License-File: LICENSE
